{"created_at": "Fri Mar 02 17:11:26 +0000 2018", "id": 969621211574689793, "id_str": "969621211574689793", "text": "@nextaa17 Niente \u00e8 una cazzata sparata sulla scia di quella detta da Salvini \ud83e\udd17", "truncated": false, "entities": {"hashtags": [], "symbols": [], "user_mentions": [{"screen_name": "nextaa17", "name": "OLIVIERO PEAQUIN", "id": 532165957, "id_str": "532165957", "indices": [0, 9]}], "urls": []}, "metadata": {"iso_language_code": "it", "result_type": "recent"}, "source": "<a href=\"http://twitter.com/download/iphone\" rel=\"nofollow\">Twitter for iPhone</a>", "in_reply_to_status_id": 969611323519664128, "in_reply_to_status_id_str": "969611323519664128", "in_reply_to_user_id": 532165957, "in_reply_to_user_id_str": "532165957", "in_reply_to_screen_name": "nextaa17", "user": {"id": 963038834, "id_str": "963038834", "name": "Paolo Agostini", "screen_name": "ago_paolo", "location": "Chiesa in Valmalenco (Sondrio)", "description": "#Architetto, #Designer & distruttore di mondi nel tempo libero.", "url": "http://t.co/4V1wvFYE5O", "entities": {"url": {"urls": [{"url": "http://t.co/4V1wvFYE5O", "expanded_url": "http://divisare.com/authors/888895897-paolo-agostini", "display_url": "divisare.com/authors/888895\u2026", "indices": [0, 22]}]}, "description": {"urls": []}}, "protected": false, "followers_count": 571, "friends_count": 1487, "listed_count": 18, "created_at": "Wed Nov 21 20:29:14 +0000 2012", "favourites_count": 2442, "utc_offset": null, "time_zone": null, "geo_enabled": true, "verified": false, "statuses_count": 2205, "lang": "it", "contributors_enabled": false, "is_translator": false, "is_translation_enabled": false, "profile_background_color": "000000", "profile_background_image_url": "http://abs.twimg.com/images/themes/theme1/bg.png", "profile_background_image_url_https": "https://abs.twimg.com/images/themes/theme1/bg.png", "profile_background_tile": false, "profile_image_url": "http://pbs.twimg.com/profile_images/378800000594657813/0b0e015c23dfa732813a61a1cb0d6962_normal.jpeg", "profile_image_url_https": "https://pbs.twimg.com/profile_images/378800000594657813/0b0e015c23dfa732813a61a1cb0d6962_normal.jpeg", "profile_banner_url": "https://pbs.twimg.com/profile_banners/963038834/1407666897", "profile_link_color": "89C9FA", "profile_sidebar_border_color": "000000", "profile_sidebar_fill_color": "000000", "profile_text_color": "000000", "profile_use_background_image": false, "has_extended_profile": true, "default_profile": false, "default_profile_image": false, "following": false, "follow_request_sent": false, "notifications": false, "translator_type": "none"}, "geo": null, "coordinates": null, "place": {"id": "df1f2b8af744e9a5", "url": "https://api.twitter.com/1.1/geo/id/df1f2b8af744e9a5.json", "place_type": "city", "name": "Chiesa in Valmalenco", "full_name": "Chiesa in Valmalenco, Lombardy", "country_code": "IT", "country": "Italy", "contained_within": [], "bounding_box": {"type": "Polygon", "coordinates": [[[9.7135464, 46.2395517], [9.8835873, 46.2395517], [9.8835873, 46.3516725], [9.7135464, 46.3516725]]]}, "attributes": {}}, "contributors": null, "is_quote_status": false, "retweet_count": 0, "favorite_count": 0, "favorited": false, "retweeted": false, "lang": "it"}
{"created_at": "Fri Mar 02 06:33:53 +0000 2018", "id": 969460768390381569, "id_str": "969460768390381569", "text": "@lauraboldrini @matteosalvinimi @mattino5 Mi risulta che Salvini, che non voto, avesse in mano il Vangelo e la Cost\u2026 https://t.co/UVH1VFnfnG", "truncated": true, "entities": {"hashtags": [], "symbols": [], "user_mentions": [{"screen_name": "lauraboldrini", "name": "laura boldrini", "id": 221902171, "id_str": "221902171", "indices": [0, 14]}, {"screen_name": "matteosalvinimi", "name": "Matteo Salvini", "id": 270839361, "id_str": "270839361", "indices": [15, 31]}, {"screen_name": "mattino5", "name": "Mattino5", "id": 1734567211, "id_str": "1734567211", "indices": [32, 41]}], "urls": [{"url": "https://t.co/UVH1VFnfnG", "expanded_url": "https://twitter.com/i/web/status/969460768390381569", "display_url": "twitter.com/i/web/status/9\u2026", "indices": [117, 140]}]}, "metadata": {"iso_language_code": "it", "result_type": "recent"}, "source": "<a href=\"http://twitter.com/download/iphone\" rel=\"nofollow\">Twitter for iPhone</a>", "in_reply_to_status_id": 969149878847836160, "in_reply_to_status_id_str": "969149878847836160", "in_reply_to_user_id": 221902171, "in_reply_to_user_id_str": "221902171", "in_reply_to_screen_name": "lauraboldrini", "user": {"id": 65968902, "id_str": "65968902", "name": "Michele Borserini", "screen_name": "maverik56", "location": "ITALY", "description": "", "url": "https://t.co/XOJ10BGODS", "entities": {"url": {"urls": [{"url": "https://t.co/XOJ10BGODS", "expanded_url": "http://www.borserini.it", "display_url": "borserini.it", "indices": [0, 23]}]}, "description": {"urls": []}}, "protected": false, "followers_count": 63, "friends_count": 286, "listed_count": 0, "created_at": "Sat Aug 15 20:15:29 +0000 2009", "favourites_count": 507, "utc_offset": 3600, "time_zone": "Rome", "geo_enabled": true, "verified": false, "statuses_count": 526, "lang": "it", "contributors_enabled": false, "is_translator": false, "is_translation_enabled": false, "profile_background_color": "9AE4E8", "profile_background_image_url": "http://pbs.twimg.com/profile_background_images/34814024/LH0107-3.JPG", "profile_background_image_url_https": "https://pbs.twimg.com/profile_background_images/34814024/LH0107-3.JPG", "profile_background_tile": true, "profile_image_url": "http://pbs.twimg.com/profile_images/1739058490/IMG_1558-1_normal.JPG", "profile_image_url_https": "https://pbs.twimg.com/profile_images/1739058490/IMG_1558-1_normal.JPG", "profile_banner_url": "https://pbs.twimg.com/profile_banners/65968902/1510501953", "profile_link_color": "0084B4", "profile_sidebar_border_color": "BDDCAD", "profile_sidebar_fill_color": "DDFFCC", "profile_text_color": "333333", "profile_use_background_image": true, "has_extended_profile": true, "default_profile": false, "default_profile_image": false, "following": false, "follow_request_sent": false, "notifications": false, "translator_type": "none"}, "geo": null, "coordinates": null, "place": {"id": "cb45f308daffbf5e", "url": "https://api.twitter.com/1.1/geo/id/cb45f308daffbf5e.json", "place_type": "city", "name": "Sondrio", "full_name": "Sondrio, Lombardia", "country_code": "IT", "country": "Italy", "contained_within": [], "bounding_box": {"type": "Polygon", "coordinates": [[[9.8238064, 46.1579823], [9.898303, 46.1579823], [9.898303, 46.2115582], [9.8238064, 46.2115582]]]}, "attributes": {}}, "contributors": null, "is_quote_status": false, "retweet_count": 0, "favorite_count": 0, "favorited": false, "retweeted": false, "lang": "it"}
{"created_at": "Wed Feb 28 18:14:53 +0000 2018", "id": 968912402937937920, "id_str": "968912402937937920", "text": "Hanno fondato LeU l\u2019altro mese per beghe nella sinistra, l\u2019altro giorno dicono che il 5 marzo fondano un nuovo part\u2026 https://t.co/5TOTTUftfC", "truncated": true, "entities": {"hashtags": [], "symbols": [], "user_mentions": [], "urls": [{"url": "https://t.co/5TOTTUftfC", "expanded_url": "https://twitter.com/i/web/status/968912402937937920", "display_url": "twitter.com/i/web/status/9\u2026", "indices": [117, 140]}]}, "metadata": {"iso_language_code": "it", "result_type": "recent"}, "source": "<a href=\"http://twitter.com/download/iphone\" rel=\"nofollow\">Twitter for iPhone</a>", "in_reply_to_status_id": null, "in_reply_to_status_id_str": null, "in_reply_to_user_id": null, "in_reply_to_user_id_str": null, "in_reply_to_screen_name": null, "user": {"id": 65968902, "id_str": "65968902", "name": "Michele Borserini", "screen_name": "maverik56", "location": "ITALY", "description": "", "url": "https://t.co/XOJ10BGODS", "entities": {"url": {"urls": [{"url": "https://t.co/XOJ10BGODS", "expanded_url": "http://www.borserini.it", "display_url": "borserini.it", "indices": [0, 23]}]}, "description": {"urls": []}}, "protected": false, "followers_count": 63, "friends_count": 286, "listed_count": 0, "created_at": "Sat Aug 15 20:15:29 +0000 2009", "favourites_count": 507, "utc_offset": 3600, "time_zone": "Rome", "geo_enabled": true, "verified": false, "statuses_count": 526, "lang": "it", "contributors_enabled": false, "is_translator": false, "is_translation_enabled": false, "profile_background_color": "9AE4E8", "profile_background_image_url": "http://pbs.twimg.com/profile_background_images/34814024/LH0107-3.JPG", "profile_background_image_url_https": "https://pbs.twimg.com/profile_background_images/34814024/LH0107-3.JPG", "profile_background_tile": true, "profile_image_url": "http://pbs.twimg.com/profile_images/1739058490/IMG_1558-1_normal.JPG", "profile_image_url_https": "https://pbs.twimg.com/profile_images/1739058490/IMG_1558-1_normal.JPG", "profile_banner_url": "https://pbs.twimg.com/profile_banners/65968902/1510501953", "profile_link_color": "0084B4", "profile_sidebar_border_color": "BDDCAD", "profile_sidebar_fill_color": "DDFFCC", "profile_text_color": "333333", "profile_use_background_image": true, "has_extended_profile": true, "default_profile": false, "default_profile_image": false, "following": false, "follow_request_sent": false, "notifications": false, "translator_type": "none"}, "geo": null, "coordinates": null, "place": {"id": "cb45f308daffbf5e", "url": "https://api.twitter.com/1.1/geo/id/cb45f308daffbf5e.json", "place_type": "city", "name": "Sondrio", "full_name": "Sondrio, Lombardia", "country_code": "IT", "country": "Italy", "contained_within": [], "bounding_box": {"type": "Polygon", "coordinates": [[[9.8238064, 46.1579823], [9.898303, 46.1579823], [9.898303, 46.2115582], [9.8238064, 46.2115582]]]}, "attributes": {}}, "contributors": null, "is_quote_status": true, "quoted_status_id": 968911116075175936, "quoted_status_id_str": "968911116075175936", "quoted_status": {"created_at": "Wed Feb 28 18:09:46 +0000 2018", "id": 968911116075175936, "id_str": "968911116075175936", "text": "Grasso a sorpresa: \u00abS\u00ec a un governo di scopo con Renzi e Berlusconi\u00bb https://t.co/JhKYZukOVu https://t.co/VF3qQcEFDC", "truncated": false, "entities": {"hashtags": [], "symbols": [], "user_mentions": [], "urls": [{"url": "https://t.co/JhKYZukOVu", "expanded_url": "http://csera.it/ddeda375Nz", "display_url": "csera.it/ddeda375Nz", "indices": [69, 92]}], "media": [{"id": 968911114296840192, "id_str": "968911114296840192", "indices": [93, 116], "media_url": "http://pbs.twimg.com/media/DXJDhmKXUAALCXo.jpg", "media_url_https": "https://pbs.twimg.com/media/DXJDhmKXUAALCXo.jpg", "url": "https://t.co/VF3qQcEFDC", "display_url": "pic.twitter.com/VF3qQcEFDC", "expanded_url": "https://twitter.com/Corriere/status/968911116075175936/photo/1", "type": "photo", "sizes": {"thumb": {"w": 150, "h": 150, "resize": "crop"}, "large": {"w": 656, "h": 492, "resize": "fit"}, "small": {"w": 656, "h": 492, "resize": "fit"}, "medium": {"w": 656, "h": 492, "resize": "fit"}}}]}, "extended_entities": {"media": [{"id": 968911114296840192, "id_str": "968911114296840192", "indices": [93, 116], "media_url": "http://pbs.twimg.com/media/DXJDhmKXUAALCXo.jpg", "media_url_https": "https://pbs.twimg.com/media/DXJDhmKXUAALCXo.jpg", "url": "https://t.co/VF3qQcEFDC", "display_url": "pic.twitter.com/VF3qQcEFDC", "expanded_url": "https://twitter.com/Corriere/status/968911116075175936/photo/1", "type": "photo", "sizes": {"thumb": {"w": 150, "h": 150, "resize": "crop"}, "large": {"w": 656, "h": 492, "resize": "fit"}, "small": {"w": 656, "h": 492, "resize": "fit"}, "medium": {"w": 656, "h": 492, "resize": "fit"}}}]}, "metadata": {"iso_language_code": "it", "result_type": "recent"}, "source": "<a href=\"http://www.corriere.it\" rel=\"nofollow\">TweetCorriereit</a>", "in_reply_to_status_id": null, "in_reply_to_status_id_str": null, "in_reply_to_user_id": null, "in_reply_to_user_id_str": null, "in_reply_to_screen_name": null, "user": {"id": 395218906, "id_str": "395218906", "name": "Corriere della Sera", "screen_name": "Corriere", "location": "Milano", "description": "L'informazione in 280 caratteri, 7 giorni su 7. Seguici per ricevere notizie, breaking news, RT dei nostri giornalisti, consigli di lettura, foto", "url": "https://t.co/h9cEgjpww3", "entities": {"url": {"urls": [{"url": "https://t.co/h9cEgjpww3", "expanded_url": "http://www.corriere.it", "display_url": "corriere.it", "indices": [0, 23]}]}, "description": {"urls": []}}, "protected": false, "followers_count": 2050350, "friends_count": 294, "listed_count": 7177, "created_at": "Fri Oct 21 10:00:47 +0000 2011", "favourites_count": 3385, "utc_offset": 3600, "time_zone": "Rome", "geo_enabled": true, "verified": true, "statuses_count": 285458, "lang": "it", "contributors_enabled": false, "is_translator": false, "is_translation_enabled": true, "profile_background_color": "EBEBEB", "profile_background_image_url": "http://pbs.twimg.com/profile_background_images/378800000019315744/d4dd074bb86b0e7a6f12e4d1bf7b933d.gif", "profile_background_image_url_https": "https://pbs.twimg.com/profile_background_images/378800000019315744/d4dd074bb86b0e7a6f12e4d1bf7b933d.gif", "profile_background_tile": false, "profile_image_url": "http://pbs.twimg.com/profile_images/844239421696368640/8du2P_fp_normal.jpg", "profile_image_url_https": "https://pbs.twimg.com/profile_images/844239421696368640/8du2P_fp_normal.jpg", "profile_banner_url": "https://pbs.twimg.com/profile_banners/395218906/1511504713", "profile_link_color": "4F48B0", "profile_sidebar_border_color": "FFFFFF", "profile_sidebar_fill_color": "F3F3F3", "profile_text_color": "25262E", "profile_use_background_image": true, "has_extended_profile": false, "default_profile": false, "default_profile_image": false, "following": true, "follow_request_sent": false, "notifications": false, "translator_type": "none"}, "geo": null, "coordinates": null, "place": null, "contributors": null, "is_quote_status": false, "retweet_count": 51, "favorite_count": 43, "favorited": false, "retweeted": false, "possibly_sensitive": false, "lang": "it"}, "retweet_count": 0, "favorite_count": 0, "favorited": false, "retweeted": false, "possibly_sensitive": false, "lang": "it"}
{"created_at": "Wed Feb 28 12:59:47 +0000 2018", "id": 968833107242770433, "id_str": "968833107242770433", "text": "Si parla pi\u00f9 del possibile CT della nazionale che del candidato premier del #PD o #ForzaItalia #welcomeInItaly #Costacurta", "truncated": false, "entities": {"hashtags": [{"text": "PD", "indices": [76, 79]}, {"text": "ForzaItalia", "indices": [82, 94]}, {"text": "welcomeInItaly", "indices": [95, 110]}, {"text": "Costacurta", "indices": [111, 122]}], "symbols": [], "user_mentions": [], "urls": []}, "metadata": {"iso_language_code": "it", "result_type": "recent"}, "source": "<a href=\"http://twitter.com/download/iphone\" rel=\"nofollow\">Twitter for iPhone</a>", "in_reply_to_status_id": null, "in_reply_to_status_id_str": null, "in_reply_to_user_id": null, "in_reply_to_user_id_str": null, "in_reply_to_screen_name": null, "user": {"id": 963038834, "id_str": "963038834", "name": "Paolo Agostini", "screen_name": "ago_paolo", "location": "Chiesa in Valmalenco (Sondrio)", "description": "#Architetto, #Designer & distruttore di mondi nel tempo libero.", "url": "http://t.co/4V1wvFYE5O", "entities": {"url": {"urls": [{"url": "http://t.co/4V1wvFYE5O", "expanded_url": "http://divisare.com/authors/888895897-paolo-agostini", "display_url": "divisare.com/authors/888895\u2026", "indices": [0, 22]}]}, "description": {"urls": []}}, "protected": false, "followers_count": 571, "friends_count": 1487, "listed_count": 18, "created_at": "Wed Nov 21 20:29:14 +0000 2012", "favourites_count": 2442, "utc_offset": null, "time_zone": null, "geo_enabled": true, "verified": false, "statuses_count": 2205, "lang": "it", "contributors_enabled": false, "is_translator": false, "is_translation_enabled": false, "profile_background_color": "000000", "profile_background_image_url": "http://abs.twimg.com/images/themes/theme1/bg.png", "profile_background_image_url_https": "https://abs.twimg.com/images/themes/theme1/bg.png", "profile_background_tile": false, "profile_image_url": "http://pbs.twimg.com/profile_images/378800000594657813/0b0e015c23dfa732813a61a1cb0d6962_normal.jpeg", "profile_image_url_https": "https://pbs.twimg.com/profile_images/378800000594657813/0b0e015c23dfa732813a61a1cb0d6962_normal.jpeg", "profile_banner_url": "https://pbs.twimg.com/profile_banners/963038834/1407666897", "profile_link_color": "89C9FA", "profile_sidebar_border_color": "000000", "profile_sidebar_fill_color": "000000", "profile_text_color": "000000", "profile_use_background_image": false, "has_extended_profile": true, "default_profile": false, "default_profile_image": false, "following": false, "follow_request_sent": false, "notifications": false, "translator_type": "none"}, "geo": null, "coordinates": null, "place": {"id": "df1f2b8af744e9a5", "url": "https://api.twitter.com/1.1/geo/id/df1f2b8af744e9a5.json", "place_type": "city", "name": "Chiesa in Valmalenco", "full_name": "Chiesa in Valmalenco, Lombardy", "country_code": "IT", "country": "Italy", "contained_within": [], "bounding_box": {"type": "Polygon", "coordinates": [[[9.7135464, 46.2395517], [9.8835873, 46.2395517], [9.8835873, 46.3516725], [9.7135464, 46.3516725]]]}, "attributes": {}}, "contributors": null, "is_quote_status": false, "retweet_count": 0, "favorite_count": 1, "favorited": false, "retweeted": false, "lang": "it"}
{"created_at": "Wed Feb 28 08:15:57 +0000 2018", "id": 968761680346968064, "id_str": "968761680346968064", "text": "Mi piacerebbe chiedere alla Meloni come mai anzich\u00e9 applicare questa tassa piatta non sarebbe stato pi\u00f9 facile abba\u2026 https://t.co/vzLsDlahIt", "truncated": true, "entities": {"hashtags": [], "symbols": [], "user_mentions": [], "urls": [{"url": "https://t.co/vzLsDlahIt", "expanded_url": "https://twitter.com/i/web/status/968761680346968064", "display_url": "twitter.com/i/web/status/9\u2026", "indices": [117, 140]}]}, "metadata": {"iso_language_code": "it", "result_type": "recent"}, "source": "<a href=\"http://twitter.com/download/android\" rel=\"nofollow\">Twitter for Android</a>", "in_reply_to_status_id": null, "in_reply_to_status_id_str": null, "in_reply_to_user_id": null, "in_reply_to_user_id_str": null, "in_reply_to_screen_name": null, "user": {"id": 900089641164046336, "id_str": "900089641164046336", "name": "Claudio", "screen_name": "Claudio79226588", "location": "Sondrio", "description": "", "url": null, "entities": {"description": {"urls": []}}, "protected": false, "followers_count": 0, "friends_count": 79, "listed_count": 0, "created_at": "Tue Aug 22 20:17:48 +0000 2017", "favourites_count": 0, "utc_offset": null, "time_zone": null, "geo_enabled": false, "verified": false, "statuses_count": 6, "lang": "it", "contributors_enabled": false, "is_translator": false, "is_translation_enabled": false, "profile_background_color": "F5F8FA", "profile_background_image_url": null, "profile_background_image_url_https": null, "profile_background_tile": false, "profile_image_url": "http://pbs.twimg.com/profile_images/946443076842684418/6EWkc7kh_normal.jpg", "profile_image_url_https": "https://pbs.twimg.com/profile_images/946443076842684418/6EWkc7kh_normal.jpg", "profile_banner_url": "https://pbs.twimg.com/profile_banners/900089641164046336/1514484588", "profile_link_color": "1DA1F2", "profile_sidebar_border_color": "C0DEED", "profile_sidebar_fill_color": "DDEEF6", "profile_text_color": "333333", "profile_use_background_image": true, "has_extended_profile": true, "default_profile": true, "default_profile_image": false, "following": false, "follow_request_sent": false, "notifications": false, "translator_type": "none"}, "geo": null, "coordinates": null, "place": null, "contributors": null, "is_quote_status": false, "retweet_count": 0, "favorite_count": 0, "favorited": false, "retweeted": false, "lang": "it"}
{"created_at": "Tue Feb 27 13:53:16 +0000 2018", "id": 968484179544625153, "id_str": "968484179544625153", "text": "@BOSSIMILANIST @MilanNewsit @berlusconi Ma ieri non voleva le 2 punte??\ud83d\ude02\ud83d\ude02\ud83d\ude02", "truncated": false, "entities": {"hashtags": [], "symbols": [], "user_mentions": [{"screen_name": "BOSSIMILANIST", "name": "BOSSI MILANIST", "id": 1950079004, "id_str": "1950079004", "indices": [0, 14]}, {"screen_name": "MilanNewsit", "name": "MilanNews.it", "id": 444812884, "id_str": "444812884", "indices": [15, 27]}, {"screen_name": "berlusconi", "name": "Silvio Berlusconi", "id": 920277002858500096, "id_str": "920277002858500096", "indices": [28, 39]}], "urls": []}, "metadata": {"iso_language_code": "it", "result_type": "recent"}, "source": "<a href=\"http://twitter.com/download/iphone\" rel=\"nofollow\">Twitter for iPhone</a>", "in_reply_to_status_id": 968483228813348865, "in_reply_to_status_id_str": "968483228813348865", "in_reply_to_user_id": 1950079004, "in_reply_to_user_id_str": "1950079004", "in_reply_to_screen_name": "BOSSIMILANIST", "user": {"id": 3338788090, "id_str": "3338788090", "name": "miky1899", "screen_name": "michele241075", "location": "Sondrio, Lombardia", "description": "", "url": null, "entities": {"description": {"urls": []}}, "protected": false, "followers_count": 384, "friends_count": 524, "listed_count": 6, "created_at": "Sun Jun 21 10:48:28 +0000 2015", "favourites_count": 10840, "utc_offset": null, "time_zone": null, "geo_enabled": true, "verified": false, "statuses_count": 8597, "lang": "it", "contributors_enabled": false, "is_translator": false, "is_translation_enabled": false, "profile_background_color": "C0DEED", "profile_background_image_url": "http://abs.twimg.com/images/themes/theme1/bg.png", "profile_background_image_url_https": "https://abs.twimg.com/images/themes/theme1/bg.png", "profile_background_tile": false, "profile_image_url": "http://pbs.twimg.com/profile_images/963447697163345921/U1oEdOoW_normal.jpg", "profile_image_url_https": "https://pbs.twimg.com/profile_images/963447697163345921/U1oEdOoW_normal.jpg", "profile_banner_url": "https://pbs.twimg.com/profile_banners/3338788090/1518538772", "profile_link_color": "1DA1F2", "profile_sidebar_border_color": "C0DEED", "profile_sidebar_fill_color": "DDEEF6", "profile_text_color": "333333", "profile_use_background_image": true, "has_extended_profile": true, "default_profile": true, "default_profile_image": false, "following": false, "follow_request_sent": false, "notifications": false, "translator_type": "none"}, "geo": null, "coordinates": null, "place": {"id": "cb45f308daffbf5e", "url": "https://api.twitter.com/1.1/geo/id/cb45f308daffbf5e.json", "place_type": "city", "name": "Sondrio", "full_name": "Sondrio, Lombardia", "country_code": "IT", "country": "Italy", "contained_within": [], "bounding_box": {"type": "Polygon", "coordinates": [[[9.8238064, 46.1579823], [9.898303, 46.1579823], [9.898303, 46.2115582], [9.8238064, 46.2115582]]]}, "attributes": {}}, "contributors": null, "is_quote_status": false, "retweet_count": 0, "favorite_count": 0, "favorited": false, "retweeted": false, "lang": "it"}
{"created_at": "Mon Feb 26 20:06:22 +0000 2018", "id": 968215685565382656, "id_str": "968215685565382656", "text": "Dalla zecca Gruber tutti contro la Meloni..Una trasmissione  inguardabile  vergogna PD.", "truncated": false, "entities": {"hashtags": [], "symbols": [], "user_mentions": [], "urls": []}, "metadata": {"iso_language_code": "it", "result_type": "recent"}, "source": "<a href=\"http://www.facebook.com/twitter\" rel=\"nofollow\">Facebook</a>", "in_reply_to_status_id": null, "in_reply_to_status_id_str": null, "in_reply_to_user_id": null, "in_reply_to_user_id_str": null, "in_reply_to_screen_name": null, "user": {"id": 480447236, "id_str": "480447236", "name": "antonello bazzi", "screen_name": "antonellobazzi", "location": "valtellina", "description": "", "url": null, "entities": {"description": {"urls": []}}, "protected": false, "followers_count": 1, "friends_count": 1, "listed_count": 0, "created_at": "Wed Feb 01 14:18:02 +0000 2012", "favourites_count": 0, "utc_offset": null, "time_zone": null, "geo_enabled": false, "verified": false, "statuses_count": 1340, "lang": "it", "contributors_enabled": false, "is_translator": false, "is_translation_enabled": false, "profile_background_color": "C0DEED", "profile_background_image_url": "http://abs.twimg.com/images/themes/theme1/bg.png", "profile_background_image_url_https": "https://abs.twimg.com/images/themes/theme1/bg.png", "profile_background_tile": false, "profile_image_url": "http://pbs.twimg.com/profile_images/1828655638/271009_212538838791461_100001060400865_641701_3487632_s_-_Copia_normal.jpg", "profile_image_url_https": "https://pbs.twimg.com/profile_images/1828655638/271009_212538838791461_100001060400865_641701_3487632_s_-_Copia_normal.jpg", "profile_link_color": "1DA1F2", "profile_sidebar_border_color": "C0DEED", "profile_sidebar_fill_color": "DDEEF6", "profile_text_color": "333333", "profile_use_background_image": true, "has_extended_profile": false, "default_profile": true, "default_profile_image": false, "following": false, "follow_request_sent": false, "notifications": false, "translator_type": "none"}, "geo": null, "coordinates": null, "place": null, "contributors": null, "is_quote_status": false, "retweet_count": 0, "favorite_count": 0, "favorited": false, "retweeted": false, "lang": "it"}
